MANIFEST.in
NOTICE
README.md
setup.py
doc/Makefile
doc/conf.py
doc/examples.rst
doc/index.rst
doc/intro.rst
doc/usage.rst
iptc/__init__.py
iptc/__init__.pyc
iptc/easy.py
iptc/errors.py
iptc/errors.pyc
iptc/ip4tc.py
iptc/ip4tc.pyc
iptc/ip6tc.py
iptc/ip6tc.pyc
iptc/util.py
iptc/util.pyc
iptc/version.py
iptc/version.pyc
iptc/xtables.py
iptc/xtables.pyc
libxtwrapper/wrapper.c
python_iptables.egg-info/PKG-INFO
python_iptables.egg-info/SOURCES.txt
python_iptables.egg-info/dependency_links.txt
python_iptables.egg-info/top_level.txt